link_stacklog/__init__.py
link_stacklog/__main__.py
link_stacklog/cli.py
link_stacklog/database.py
link_stacklog/links.py
link_stacklog/stack.py
link_stacklog-0.2.1.dist-info/LICENSE
link_stacklog-0.2.1.dist-info/METADATA
link_stacklog-0.2.1.dist-info/WHEEL
link_stacklog-0.2.1.dist-info/entry_points.txt
link_stacklog-0.2.1.dist-info/top_level.txt
link_stacklog-0.2.1.dist-info/RECORD
