Metadata-Version: 2.1
Name: link-stacklog
Version: 0.2.1
Summary: Link backlog management utility using a stack style interface
Author: theFestest
License: Apache-2.0
Project-URL: Homepage, https://github.com/theFestest/link-stacklog
Project-URL: Changelog, https://github.com/theFestest/link-stacklog/releases
Project-URL: Issues, https://github.com/theFestest/link-stacklog/issues
Project-URL: CI, https://github.com/theFestest/link-stacklog/actions
Classifier: License :: OSI Approved :: Apache Software License
Requires-Python: >=3.8
License-File: LICENSE
Requires-Dist: click
Requires-Dist: requests
Requires-Dist: beautifulsoup4
Requires-Dist: sqlite-utils
Provides-Extra: test
Requires-Dist: pytest ; extra == 'test'
